{
  "list": [
    {
      "id": "7dc0",
      "list": "Hello"
    },
    {
      "id": "89cc",
      "list": "Biggie"
    },
    {
      "id": "9e85",
      "list": "Sing"
    },
    {
      "id": "748d",
      "list": "TOTO"
    },
    {
      "id": "937c",
      "list": "Orio"
    },
    {
      "id": "1b60",
      "list": "Sing"
    },
    {
      "id": "2319",
      "list": "Sing"
    },
    {
      "id": "dc3f",
      "list": "Sing"
    },
    {
      "id": "93af",
      "list": "ggg"
    },
    {
      "id": "c70f",
      "list": "dgdg"
    },
    {
      "id": "3ccf",
      "list": "fjjmrm"
    }
  ]
}